shell_themer/__init__.py
shell_themer/__main__.py
shell_themer/agents.py
shell_themer/exceptions.py
shell_themer/interpolator.py
shell_themer/parsers.py
shell_themer/theme.py
shell_themer/themer.py
shell_themer/utils.py
shell_themer/version.py
shell_themer-0.7.0.dist-info/LICENSE
shell_themer-0.7.0.dist-info/METADATA
shell_themer-0.7.0.dist-info/WHEEL
shell_themer-0.7.0.dist-info/entry_points.txt
shell_themer-0.7.0.dist-info/top_level.txt
shell_themer-0.7.0.dist-info/RECORD
