Metadata-Version: 2.1
Name: shell-themer
Version: 0.7.0
Summary: Use consistent color themes for a variety of command line tools.
Author-email: Jared Crapo <jared@kotfu.net>
License: MIT License
Project-URL: homepage, https://github.com/kotfu/shell-themer
Project-URL: repository, https://github.com/kotfu/shell-themer
Keywords: shell,bash,theme,command line
Classifier: Development Status :: 3 - Alpha
Classifier: Environment :: Console
Classifier: Operating System :: OS Independent
Classifier: Topic :: Utilities
Classifier: Intended Audience :: Developers
Classifier: License :: OSI Approved :: MIT License
Classifier: Programming Language :: Python :: 3 :: Only
Classifier: Programming Language :: Python :: 3.9
Classifier: Programming Language :: Python :: 3.10
Classifier: Programming Language :: Python :: 3.11
Classifier: Programming Language :: Python :: 3.12
Classifier: Programming Language :: Python :: 3.13
Requires-Python: >=3.9
License-File: LICENSE
Requires-Dist: rich
Requires-Dist: rich_argparse
Requires-Dist: tomlkit
Provides-Extra: dev
Requires-Dist: build; extra == "dev"
Requires-Dist: pytest; extra == "dev"
Requires-Dist: pytest-mock; extra == "dev"
Requires-Dist: pytest-cov; extra == "dev"
Requires-Dist: codecov; extra == "dev"
Requires-Dist: pylint; extra == "dev"
Requires-Dist: ruff; extra == "dev"
Requires-Dist: wheel; extra == "dev"
Requires-Dist: twine; extra == "dev"
Requires-Dist: rope; extra == "dev"
Requires-Dist: invoke; extra == "dev"
